MetAromatic/__init__.py
MetAromatic/algorithm.py
MetAromatic/aliases.py
MetAromatic/consts.py
MetAromatic/errors.py
MetAromatic/get_aromatic_midpoints.py
MetAromatic/get_batch.py
MetAromatic/get_bridge.py
MetAromatic/get_pair.py
MetAromatic/load_resources.py
MetAromatic/lone_pair_interpolators.py
MetAromatic/models.py
MetAromatic/runner.py
MetAromatic/utils.py
metaromatic-1.7.0.dist-info/licenses/LICENSE
metaromatic-1.7.0.dist-info/METADATA
metaromatic-1.7.0.dist-info/WHEEL
metaromatic-1.7.0.dist-info/entry_points.txt
metaromatic-1.7.0.dist-info/top_level.txt
metaromatic-1.7.0.dist-info/RECORD
