Metadata-Version: 2.4
Name: MetAromatic
Version: 1.7.0
Summary: MetAromatic algorithm
Author: David Weber
Classifier: Programming Language :: Python :: 3
Classifier: License :: OSI Approved :: GNU General Public License v3 (GPLv3)
Classifier: Operating System :: OS Independent
Requires-Python: >=3.11
License-File: LICENSE
Requires-Dist: click
Requires-Dist: networkx
Requires-Dist: numpy
Requires-Dist: pydantic
Requires-Dist: pymongo
Requires-Dist: types-networkx
Requires-Dist: typing_extensions
Dynamic: license-file
